chinus_decorators/__init__.py
chinus_decorators/warning/__init__.py
chinus_decorators/warning/not_used_return_value.py
chinus_decorators-1.0.3.dist-info/METADATA
chinus_decorators-1.0.3.dist-info/WHEEL
chinus_decorators-1.0.3.dist-info/top_level.txt
chinus_decorators-1.0.3.dist-info/RECORD
